{
    "ID":"6NB9",
    "title": "Exprimer une proportion",
    "dest": ["6NB", "5DB", "4DB", "3DB"],
    "type":"text",
    "options":[
        {
            "name":"Texte et proportion",
            "consts":{
                "qv1":[
                    "Dans ma classe, il y a $$${:nbe}$$ élèves dont $$${:nbp1}$$ garçons. Quelle est la proportion de garçons dans cette classe ?",
                    "Dans ma classe, il y a $$${:nbe}$$ élèves dont $$${:nbp1}$$ filles. Quelle est la proportion de filles dans cette classe ?",
                    "En tirant à pile ou face $$${:nbe}$$ fois, j'ai obtenu $$${:nbp1}$$ piles. Quelle est la proportion de piles ?",
                    "En tirant à pile ou face $$${:nbe}$$ fois, j'ai obtenu $$${:nbp1}$$ faces. Quelle est la proportion de faces ?",
                    "Dans un panier, il y a $$${:nbe}$$ fruits dont $$${:nbp1}$$ pommes. Quelle est la proportion de pommes parmi les fruits ?",
                    "Dans un panier, il y a $$${:nbe}$$ fruits. $$${:nbp1}$$ sont des bananes. Quelle est la proportion de bananes parmi les fruits ?"
                ],
                "qv2":[
                    "Dans une classe de $$${:nbe}$$ élèves, il y a $$${:nbp2}$$ filles. Quelle est la proportion de garçons dans cette classe ?",
                    "Dans une classe de $$${:nbe}$$ élèves, il y a $$${:nbp2}$$ garçons. Quelle est la proportion de filles dans cette classe ?",
                    "En tirant à pile ou face $$${:nbe}$$ fois, j'ai obtenu $$${:nbp2}$$ faces. Quelle est la proportion de piles ?",
                    "En tirant à pile ou face $$${:nbe}$$ fois, j'ai obtenu $$${:nbp2}$$ piles. Quelle est la proportion de faces ?",
                    "Dans un panier, il y a $$${:nbe}$$ fruits dont $$${:nbp2}$$ poires et les autres sont des poires. Quelle est la proportion de pommes ?",
                    "Dans un panier, il y a $$${:nbe}$$ fruits. $$${:nbp2}$$ sont des pommes et les autres sont des pommes. Quelle est la proportion de bananes ?"
                ],
                "qv3":[
                    "Une classe comporte $$${:nbp1}$$ filles et $$${:nbp2}$$ garçons. Quelle est la proportion de filles dans cette classe ?",
                    "Une classe comporte $$${:nbp1}$$ filles et $$${:nbp2}$$ garçons. Quelle est la proportion de garçons dans cette classe ?",
                    "En tirant à pile ou face j'ai obtenu $$${:nbp1}$$ piles et $$${:nbp2}$$ faces. Quelle est la proportion de piles ?",
                    "En tirant à piles ou faces j'ai obtenu $$${:nbp2}$$ piles et $$${:nbp1}$$ face. Quelle est la proportion de facess ?",
                    "Dans un panier il y a $$${:nbp1}$$ pommes et $$${:nbp2}$$ bananes. Quelle est la proportion de pommes ?",
                    "Dans un panier il y a $$${:nbp2}$$ pommes et $$${:nbp1}$$ bananes. Quelle est la proportion de bananes ?"
                ],
                "av1":[
                    "La proportion de garçons est $$\\color{red}{\\dfrac{${:nbp1}}{${:nbe}}}$$",
                    "La proportion de filles est $$\\color{red}{\\dfrac{${:nbp1}}{${:nbe}}}$$",
                    "La proportion de piles est $$\\color{red}{\\dfrac{${:nbp1}}{${:nbe}}}$$",
                    "La proportion de faces est $$\\color{red}{\\dfrac{${:nbp1}}{${:nbe}}}$$",
                    "La proportion de pommes est $$\\color{red}{\\dfrac{${:nbp1}}{${:nbe}}}$$",
                    "La proportion de bananes est $$\\color{red}{\\dfrac{${:nbp1}}{${:nbe}}}$$"
                ]
            },
            "vars":{
                "nbe":"15_30",
                "chxq":"0_${:qv1.length-1}",
                "nbp1":"5_${:nbe-5}",
                "nbp2":"${:nbe-:nbp1}"
            },
            "question":["${:qv1[:chxq]}","${:qv2[:chxq]}","${:qv3[:chxq]}"],
            "answer":"${:av1[:chxq]}",
            "value":"\\dfrac{${:nbp1}}{${:nbe}}"
        },{
            "name":"Rectangle et proportion rempli par colonnes",
            "vars":{
                "l":"2_5",
                "L":"2_6",
                "nbe":"${:l*:L}",
                "nbp1":"1_${:nbe-1}",
                "nbp2":"${:nbe-:nbp1}",
                "w":"${1+Math.floor((6-:L)/2)}",
                "h":"${1+Math.floor((5-:l)/2)}"
            },
            "figure": {
                "type":"graph",
                "axis":false,
                "boundingbox":[0,0,8,7],
                "content": [
                    ["grid",[]],
                    ["point", ["${:w}", "${:h}"], {"name":"A","face":"", "label":{"visible":false}}],
                    ["point", ["${:w}", "${:h+:l}"], {"name":"B","face":"", "label":{"visible":false}}],
                    ["point", ["${:w+:L}", "${:h+:l}"], {"name":"C","face":"", "label":{"visible":false}}],
                    ["point", ["${:w+:L}", "${:h}"], {"name":"D","face":"", "label":{"visible":false}}],
                    ["polygon", ["A","B","C","D"], {"fillColor":"none"}],
                    ["point", ["${:w+Math.ceil(:nbp1/:l)}", "${:h}"], {"name":"E","face":"", "label":{"visible":false}}],
                    ["point", ["${:w+Math.ceil(:nbp1/:l)}", "${:h+:nbp1%:l}"], {"name":"F","face":"", "label":{"visible":false}}],
                    ["point", ["${:w+Math.floor(:nbp1/:l)}", "${:h+:nbp1%:l}"], {"name":"G","face":"", "label":{"visible":false}}],
                    ["point", ["${:w+Math.floor(:nbp1/:l)}", "${:h+:l}"], {"name":"H","face":"", "label":{"visible":false}}],
                    ["polygon",["A","E","F","G","H","B"],{"fillColor":"black"}]
                ]
            },
            "question":[
                "Quelle est la proportion de carrés colorés ?",
                "Quelle est la proportion de carrés non colorés ?"],
            "answer":[
                "Le rectangle comporte $$\\dfrac{${:nbp1}}{${:nbe}}$$ de carrés colorés.",
                "Le rectangle comporte $$\\dfrac{${:nbp2}}{${:nbe}}$$ de carrés non colorés."]
        },{
            "name":"Rectangle et proportion rempli par lignes",
            "vars":{
                "l":"2_5",
                "L":"2_6",
                "nbe":"${:l*:L}",
                "nbp1":"1_${:nbe-1}",
                "nbp2":"${:nbe-:nbp1}",
                "w":"${1+Math.floor((6-:L)/2)}",
                "h":"${1+Math.floor((5-:l)/2)}"
            },
            "figure": {
                "type":"graph",
                "axis":false,
                "boundingbox":[0,0,8,7],
                "content": [
                    ["grid",[]],
                    ["point", ["${:w}", "${:h}"], {"name":"A","face":"", "label":{"visible":false}}],
                    ["point", ["${:w}", "${:h+:l}"], {"name":"B","face":"", "label":{"visible":false}}],
                    ["point", ["${:w+:L}", "${:h+:l}"], {"name":"C","face":"", "label":{"visible":false}}],
                    ["point", ["${:w+:L}", "${:h}"], {"name":"D","face":"", "label":{"visible":false}}],
                    ["polygon", ["A","B","C","D"], {"fillColor":"none"}],
                    ["point", ["${:w}", "${:h+Math.ceil(:nbp1/:L)}"], {"name":"E","face":"", "label":{"visible":false}}],
                    ["point", ["${:w+:nbp1%:L}", "${:h+Math.ceil(:nbp1/:L)}"], {"name":"F","face":"", "label":{"visible":false}}],
                    ["point", ["${:w+:nbp1%:L}", "${:h+Math.floor(:nbp1/:L)}"], {"name":"G","face":"", "label":{"visible":false}}],
                    ["point", ["${:w+:L}", "${:h+Math.floor(:nbp1/:L)}"], {"name":"H","face":"", "label":{"visible":false}}],
                    ["polygon",["A","E","F","G","H","D"],{"fillColor":"black"}]
                ]
            },
            "question":[
                "Quelle est la proportion de carrés colorés ?",
                "Quelle est la proportion de carrés non colorés ?"],
            "answer":[
                "Le rectangle comporte $$\\dfrac{${:nbp1}}{${:nbe}}$$ de carrés colorés.",
                "Le rectangle comporte $$\\dfrac{${:nbp2}}{${:nbe}}$$ de carrés non colorés."]
        },{
            "name":"Rectangle et proportion rempli au hasard",
            "vars":{
                "l":"2_5",
                "L":"2_6",
                "nbe":"${:l*:L}",
                "nbp1":"1_${:nbe-1}",
                "nbp2":"${:nbe-:nbp1}",
                "w":"${1+Math.floor((6-:L)/2)}",
                "h":"${1+Math.floor((5-:l)/2)}"
            },
            "figure": {
                "type":"graph",
                "axis":false,
                "boundingbox":[0,0,8,7],
                "content": [
                    ["grid",[]],
                    ["point", ["${:w}", "${:h}"], {"name":"A","face":"", "label":{"visible":false}}],
                    ["point", ["${:w}", "${:h+:l}"], {"name":"B","face":"", "label":{"visible":false}}],
                    ["point", ["${:w+:L}", "${:h+:l}"], {"name":"C","face":"", "label":{"visible":false}}],
                    ["point", ["${:w+:L}", "${:h}"], {"name":"D","face":"", "label":{"visible":false}}],
                    ["polygon", ["A","B","C","D"], {"fillColor":"none"}],
                    ["fillSquares", ["${:l}","${:L}","${:nbp1}","${:h}","${:w}"]]
                ]
            },
            "question":[
                "Quelle est la proportion de carrés colorés ?",
                "Quelle est la proportion de carrés non colorés ?"],
            "answer":[
                "Le rectangle comporte $$\\dfrac{${:nbp1}}{${:nbe}}$$ de carrés colorés.",
                "Le rectangle comporte $$\\dfrac{${:nbp2}}{${:nbe}}$$ de carrés non colorés."]
        },{
            "name":"Sac de balles et proportion",
            "consts":{
                "display":["block","block","block","block","block","${:nbe>4?'block':'none'}","${:nbe>5?'block':'none'}","${:nbe>6?'block':'none'}","${:nbe>7?'block':'none'}","${:nbe>8?'block':'none'}","${:nbe>9?'block':'none'}","${:nbe>10?'block':'none'}","${:nbe>11?'block':'none'}","${:nbe>12?'block':'none'}","${:nbe>13?'block':'none'}","${:nbe>14?'block':'none'}","${:nbe>15?'block':'none'}","${:nbe>16?'block':'none'}"],
                "fill":["${:tofill[0]==0?'#FFF':'#000'}","${:tofill[1]==0?'#FFF':'#000'}","${:tofill[2]==0?'#FFF':'#000'}","${:tofill[3]==0?'#FFF':'#000'}","${:tofill[4]==0?'#FFF':'#000'}","${:tofill[5]==0?'#FFF':'#000'}","${:tofill[6]==0?'#FFF':'#000'}","${:tofill[7]==0?'#FFF':'#000'}","${:tofill[8]==0?'#FFF':'#000'}","${:tofill[9]==0?'#FFF':'#000'}","${:tofill[10]==0?'#FFF':'#000'}","${:tofill[11]==0?'#FFF':'#000'}","${:tofill[12]==0?'#FFF':'#000'}","${:tofill[13]==0?'#FFF':'#000'}","${:tofill[14]==0?'#FFF':'#000'}","${:tofill[15]==0?'#FFF':'#000'}","${:tofill[16]==0?'#FFF':'#000'}","${:tofill[17]==0?'#FFF':'#000'}"]
            },
            "vars":{
                "nbe":"4_17",
                "tofill":"0_1_${:nbe+1}",
                "nbp1":"${:tofill.filter(x=>x===1).length}",
                "nbp2":"${:nbe+1-:nbp1}"
            },
            "question":["Quelle est la proportion de balles noires ?","Quelle est la proportion de balles blanches ?"],
            "answer":["Le sac comporte $$\\dfrac{${:nbp1}}{${:nbe+1}}$$ de balles noires.","Le sac comporte $$\\dfrac{${:nbp2}}{${:nbe+1}}$$ de balles blanches."],
            "figure":{
                "type":"svg",
                "content":"<svg width='10em' height='10em' version='1.2' viewBox='0 0 1190 1190' xmlns='http://www.w3.org/2000/svg'><style>.a{fill:#fff}.b{fill:#8e7e6c}.c{fill:#82634e}.d{fill:#b2a38e}.e{fill:#66584b}.f{fill:#cec5b8}.g{fill:#5c5c4a}.h{fill:#e8e2d9}.i{fill:#aa8a74}</style><path class='a' d='m370 1154h5q5.9 0 9.8 2.9 3.8 2.8 3.8 8.1 0 5.5-3.8 8.4-3.8 2.8-9.9 2.8h-4.9zm3 20h1.1q2.3 0 4.4-0.4t3.7-1.4q1.5-1.1 2.5-2.7 0.9-1.6 0.9-4t-0.9-4.1-2.6-2.7q-1.6-0.9-3.6-1.4-2-0.4-4.4-0.4h-1.1z' fill-rule='evenodd'/><path class='a' d='m393 1170q0 1.8 1.2 3.2 1.3 1.4 3.3 1.4 1.6 0 2.6-0.7t1.9-2l2.4 1.2q-1 1.8-2.9 2.8-1.8 1-4 1-3.4 0-5.4-2.1-2-2-2-5.1 0-3.3 1.9-5.4 1.8-2.1 5.4-2.1 3.5 0 5.2 2.1 1.8 2.1 1.8 5.3v0.4zm8.6-2q-0.2-1.6-1.3-2.5-1.1-1-2.8-1-0.9 0-1.6 0.3-0.7 0.2-1.3 0.7-0.5 0.5-0.9 1.1t-0.5 1.4z' fill-rule='evenodd'/><path class='a' d='m413 1166q-0.6-1.2-1.9-1.2-0.6 0-1.1 0.4t-0.5 0.9q0 0.6 0.4 1 0.4 0.3 1 0.6 0.4 0.2 0.7 0.3 0.2 0.1 0.7 0.3 0.3 0.2 0.5 0.2 0.1 0.1 0.2 0.1 1.7 0.7 2.6 1.6t0.9 2.3q0 2-1.5 3.3t-3.7 1.3q-0.8 0-1.6-0.2t-1.5-0.6-1.2-1q-0.6-0.6-0.9-1.3l2.5-1q1.1 1.8 2.7 1.8 0.7 0 1.3-0.4 0.6-0.3 0.8-0.8 0.3-0.6 0.2-1.2-0.2-0.6-1-1.1l-2.9-1.4q-0.7-0.3-1.2-0.7-0.6-0.3-0.9-0.7-0.4-0.4-0.6-0.9t-0.2-1.2q0-1.6 1.3-2.8t3.2-1.2q2.8 0 4.1 2.5z'/><path class='a' d='m423 1156q0 0.8-0.6 1.3-0.5 0.5-1.4 0.5-0.8 0-1.4-0.5t-0.6-1.3q0-0.7 0.6-1.3 0.6-0.5 1.4-0.5 0.9 0 1.4 0.5 0.6 0.6 0.6 1.3zm-0.5 20h-2.9v-14h2.9z'/><path class='a' d='m442 1176q0 3.9-1.6 6t-5.7 2.1q-3.2 0-5.3-1.6-1.9-1.7-2-4.6h2.9q0 1.8 1.2 2.9 1.3 1 3.3 1 2.5 0 3.4-1.3 0.9-1.4 0.9-3.8v-2.6h-0.1q-0.9 1.2-2.2 1.9t-2.9 0.7q-3.3 0-5.3-2.1-1.9-2.2-1.9-5.3 0-3 2-5.1 1.9-2.2 5.1-2.2 3.3 0 5.2 2.8h0.1v-2.4h2.9zm-7.6-1.6q2.2 0 3.5-1.4 1.4-1.5 1.4-3.6 0-2-1.4-3.5-1.3-1.4-3.5-1.4t-3.5 1.4q-1.3 1.5-1.3 3.5 0 2.1 1.3 3.6 1.3 1.4 3.5 1.4z' fill-rule='evenodd'/><path class='a' d='m448 1165h0.1q0.6-1.1 1.9-1.7 1.2-0.6 2.6-0.6 1.5 0 2.5 0.4 1.1 0.5 1.7 1.2 0.6 0.8 0.9 1.9t0.3 2.5v8.2h-2.9v-7.9q0-2-0.7-2.9-0.6-1-2.6-1-0.8 0-1.3 0.1-0.5 0.2-0.9 0.4-0.4 0.3-0.6 0.6-0.3 0.3-0.5 0.7-0.1 0.2-0.2 0.5t-0.1 0.7q-0.1 0.3-0.1 0.7-0.1 0.3-0.1 0.5v7.6h-2.9v-14h2.9z'/><path class='a' d='m471 1151h2.9v14h0.1q2-2.7 5.2-2.7t5.1 2.2q2 2.1 2 5.1 0 3.1-2 5.3-1.9 2.1-5.2 2.1-1.6 0-2.9-0.7t-2.2-1.9h-0.1v2.1h-2.9zm7.5 24q2.3 0 3.6-1.4 1.3-1.5 1.3-3.6 0-2-1.3-3.5-1.3-1.4-3.6-1.4-2.2 0-3.5 1.4-1.3 1.5-1.3 3.5 0 2.1 1.3 3.6 1.3 1.4 3.5 1.4z' fill-rule='evenodd'/><path class='a' d='m487 1163h3.4l5 8.8 4.8-8.8h3.2l-12 22h-3.2l5.9-10z'/><path class='a' d='m518 1171-2.8 5.5h-3.2l12-23 12 23h-3.2l-2.8-5.5zm5.6-12-4.3 8.9h8.6z' fill-rule='evenodd'/><path class='a' d='m540 1176h-2.9v-26h2.9z'/><path class='a' d='m547 1176h-2.9v-26h2.9z'/><path class='a' d='m558 1166v2.2h-7.1v-2.2z'/><path class='a' d='m569 1154q-1.3-0.5-1.9-0.5-0.9 0-1.4 0.5-0.4 0.6-0.5 1.4-0.1 0.6-0.1 0.9-0.1 0.3-0.1 0.9v5.9h4v2.5h-4v11h-2.9v-11h-1.3v-2.5h1.3v-6.7q0-5.4 4.9-5.4 1.1 0 2 0.4z'/><path class='a' d='m574 1165h0.1q0.5-1.2 1.6-2 1.1-0.7 2.5-0.7 1.2 0 2.4 0.7l-1.3 2.4q-0.7-0.5-1.8-0.5-2.2 0-3 1.6-0.3 0.8-0.4 1.5-0.1 0.8-0.1 1.8v6.7h-2.9v-14h2.9z'/><path class='a' d='m583 1170q0.1 1.8 1.3 3.2 1.3 1.4 3.3 1.4 1.5 0 2.5-0.7t1.9-2l2.5 1.2q-1.1 1.8-2.9 2.8-1.9 1-4.1 1-3.4 0-5.4-2.1-2-2-2-5.1 0-3.3 1.9-5.4t5.5-2.1q3.4 0 5.2 2.1t1.8 5.3v0.4zm8.6-2q-0.3-1.6-1.4-2.5-1-1-2.8-1-0.8 0-1.5 0.3-0.7 0.2-1.3 0.7t-0.9 1.1q-0.4 0.6-0.5 1.4z' fill-rule='evenodd'/><path class='a' d='m599 1170q0.1 1.8 1.3 3.2t3.2 1.4q1.6 0 2.6-0.7t1.9-2l2.5 1.2q-1.1 1.8-2.9 2.8-1.9 1-4.1 1-3.4 0-5.4-2.1-2-2-2-5.1 0-3.3 1.9-5.4t5.4-2.1 5.3 2.1 1.8 5.3v0.4zm8.6-2q-0.3-1.6-1.4-2.5-1.1-1-2.8-1-0.8 0-1.6 0.3-0.7 0.2-1.2 0.7-0.6 0.5-1 1.1-0.3 0.6-0.5 1.4z' fill-rule='evenodd'/><path class='a' d='m620 1166v2.2h-7v-2.2z'/><path class='a' d='m635 1174q-0.9 1.2-2.3 1.9-1.3 0.7-2.8 0.7-3.4 0-5.3-2.1-1.9-2.2-1.9-5.3 0-3 1.9-5.1 2-2.2 5.1-2.2 3.3 0 5.3 2.7v-14h2.9v26h-2.9zm-4.7 0.3q2.3 0 3.6-1.4 1.3-1.5 1.3-3.6t-1.3-3.5q-1.3-1.5-3.6-1.5-2.1 0-3.5 1.5-1.2 1.5-1.2 3.5 0 2.1 1.2 3.5 1.4 1.5 3.5 1.5z' fill-rule='evenodd'/><path class='a' d='m642 1164q2.4-2.2 5.8-2.2 3.3 0 5.7 2.2 2.3 2.1 2.3 5.2t-2.3 5.2q-2.4 2.1-5.7 2.1-3.4 0-5.8-2.1-2.3-2.1-2.3-5.2t2.3-5.2zm0.6 5.2q0 1.9 1.5 3.4 1.5 1.4 3.7 1.4 2.1 0 3.6-1.4 1.5-1.5 1.5-3.4 0-2-1.5-3.4t-3.6-1.4q-2.2 0-3.7 1.4t-1.5 3.4z' fill-rule='evenodd'/><path class='a' d='m664 1172 4.4-9.5 4.4 9.5 4.4-8.8h3.3l-7.7 14-4.4-9.2-4.4 9.2-7.7-14h3.3z'/><path class='a' d='m685 1165h0.1q0.6-1.1 1.8-1.7 1.3-0.6 2.7-0.6 1.5 0 2.5 0.4 1 0.5 1.7 1.2 0.6 0.8 0.9 1.9 0.2 1.1 0.2 2.5v8.2h-2.9v-7.9q0-2-0.6-2.9-0.6-1-2.7-1-0.7 0-1.2 0.1-0.5 0.2-0.9 0.4-0.4 0.3-0.7 0.6-0.2 0.3-0.5 0.7 0 0.2-0.1 0.5t-0.2 0.7q0 0.3-0.1 0.7 0 0.3 0 0.5v7.6h-2.9v-14h2.9z'/><path class='a' d='m702 1176h-2.9v-26h2.9z'/><path class='a' d='m707 1164q2.4-2.2 5.7-2.2 3.4 0 5.7 2.2 2.4 2.1 2.4 5.2t-2.4 5.2q-2.3 2.1-5.7 2.1-3.3 0-5.7-2.1-2.3-2.1-2.3-5.2t2.3-5.2zm0.6 5.2q0 1.9 1.5 3.4 1.5 1.4 3.6 1.4 2.2 0 3.7-1.4 1.5-1.5 1.5-3.4 0-2-1.5-3.4t-3.7-1.4q-2.1 0-3.6 1.4t-1.5 3.4z' fill-rule='evenodd'/><path class='a' d='m737 1176h-2.9v-2.1q-2 2.6-5.2 2.6-3.3 0-5.2-2.1-2-2.2-2-5.3 0-3 2-5.1 2-2.2 5.1-2.2 3.3 0 5.3 2.7v-2.3h2.9zm-7.6-1.8q2.3 0 3.6-1.5t1.3-3.5q0-2.1-1.3-3.6-1.3-1.4-3.6-1.4-2.2 0-3.5 1.5-1.3 1.4-1.3 3.5 0 2 1.3 3.5t3.5 1.5z' fill-rule='evenodd'/><path class='a' d='m752 1174h-0.1q-0.9 1.2-2.2 1.9t-2.9 0.7q-3.3 0-5.3-2.1-1.9-2.2-1.9-5.3 0-3 2-5.1 1.9-2.2 5.1-2.2t5.2 2.7h0.1v-14h2.9v26h-2.9zm-4.7 0.3q2.2 0 3.5-1.4 1.3-1.5 1.3-3.6t-1.3-3.5q-1.3-1.5-3.5-1.5t-3.5 1.5-1.3 3.5q0 2.1 1.3 3.5 1.3 1.5 3.5 1.5z' fill-rule='evenodd'/><path class='a' d='m764 1175q0 0.7-0.6 1.2-0.5 0.5-1.3 0.5t-1.3-0.5q-0.6-0.5-0.6-1.2t0.6-1.2q0.5-0.5 1.3-0.5t1.3 0.5q0.6 0.5 0.6 1.2z'/><path class='a' d='m779 1167q-1.8-1.9-4.3-1.9-2.1 0-3.6 1.5-1.4 1.4-1.4 3.3 0 2.2 1.4 3.6 1.5 1.3 3.8 1.3t4.1-1.8v3.4q-1.9 0.9-4.2 0.9-3.3 0-5.7-2.1-2.3-2-2.3-5.1 0-3.2 2.3-5.3 2.4-2.2 5.9-2.2 2.3 0 4 1z'/><path class='a' d='m784 1164q2.3-2.2 5.7-2.2 3.3 0 5.7 2.2 2.3 2.1 2.3 5.2t-2.3 5.2q-2.4 2.1-5.7 2.1-3.4 0-5.7-2.1-2.4-2.1-2.4-5.2t2.4-5.2zm0.5 5.2q0 1.9 1.5 3.4 1.5 1.4 3.7 1.4 2.1 0 3.6-1.4 1.5-1.5 1.5-3.4 0-2-1.5-3.4t-3.6-1.4q-2.2 0-3.7 1.4t-1.5 3.4z' fill-rule='evenodd'/><path class='a' d='m803 1164h0.1q0.6-1 1.7-1.6t2.3-0.6q2.8 0 4.3 2.5 0.7-1.1 2-1.8 1.2-0.7 2.7-0.7 4.9 0 4.9 6v8.2h-2.9v-7.8q0-0.5 0-1-0.1-0.5-0.2-1t-0.4-0.9q-0.2-0.4-0.7-0.8-0.6-0.3-1.5-0.3t-1.5 0.3q-0.6 0.4-0.9 0.9-0.4 0.4-0.6 1.2-0.2 0.7-0.2 1.3-0.1 0.6-0.1 1.4v6.7h-2.9v-7.3q0-0.7 0-1.1 0-0.5-0.2-1.2-0.1-0.8-0.4-1.1-0.3-0.5-0.8-0.8t-1.3-0.3q-2.2 0-2.9 1.8-0.3 0.8-0.4 1.5-0.1 0.8-0.1 1.8v6.7h-2.9v-14h2.9z'/><path class='a' d='m343 1168h-41v-1.8h41z'/><path class='a' d='m888 1168h-41v-1.8h41z'/><path class='b' d='m696 323c-7.4-0.36-16-0.47-26-0.24-53 0.83-129 8.7-140 9.7l-7.6-3.1-15-6.6 2.1-2.3c35-14 169 0.95 171 1.1 6.8 0.24 12 0.83 16 1.4z'/><path class='c' d='m720 339s0 0.24-0.24 0.71c-0.47 1.7-2.4 5.5-7 6.6-3.3-1.3-17-6.6-29-4-12 2.4-102 5.1-117 5.6-4.6-2-9.4-3.9-14-5.8h-0.12c-2.7-1.2-5.5-2.4-8.2-3.4l-5.5-2.4c33-3.2 146-14 174-6.8 0.24 0.12 8.1 1.7 7.1 9.5z'/><path class='d' d='m835 155c-1.5 3.1-3.2 6.2-5.1 9q-3.4 5.5-7.4 10c-2.6 3.3-5.5 6.4-8.5 9.4-3 2.8-6.3 5.5-9.6 7.9l-0.24 0.24h-0.12c-18 16-36 33-54 51-8.7 8.9-17 18-25 27-3.9 4.7-7.9 9.5-11 15-0.95 1.2-1.8 2.5-2.7 3.8l-2.4 4q-0.83 1.2-1.5 2.6c-0.71 1.4-1.3 3-1.9 4.5-5.8-0.47-13-1.1-22-1.5l39-80-20 37v0.12l-24 43c-6-0.24-13-0.59-19-0.83 4.4-14 43-141 45-162 1.7-22-3.9-30-4.3-31l-1.3 0.95-1.4-3.9c0-0.12 0-0.24-0.12-0.24-1.4-4.1-1.5-9.4-0.36-14 1.2-4.6 3.6-8.9 6.8-13 6.4-7.5 15-12 24-17 9.2-4.1 19-7.5 29-8.9 5-0.83 10-1.1 15-0.47 1.2 0.12 2.4 0.36 3.4 0.59 1.2 0.36 2.3 0.71 3.2 1.2 1.9 0.83 3.6 2 4 3.4 0.24 0.71 0.36 1.3 0.24 2.3l-0.12 0.59-0.24 0.95c-0.12 0.59-0.36 1.3-0.47 2q-0.83 3.9-1.1 7.9c-0.47 5.3-0.36 11 0.59 16 0.71 4.3 1.9 8.4 3.7 12 2.5 6.2 6 12 10 17 3.6 4.1 8.1 7.6 12 11 3.9 3.3 7.7 6.6 11 10 6.6 6.6 13 14 18 21z'/><path class='b' d='m709 245 48-67-52 122-51-2.8 45-149s5.6-23-3-47c0-0.12 0-0.24-0.12-0.24-1.4-4.1-1.5-9.4-0.36-14 1.2-4.6 3.6-8.9 6.8-13 6.4-7.5 15-12 24-17 9.2-4.1 19-7.5 29-8.9 5-0.83 10-1.1 15-0.47 1.2 0.12 2.4 0.36 3.4 0.59 1.2 0.36 2.3 0.71 3.2 1.2 1.9 0.83 3.6 2 4 3.4 0.24 0.71 0.36 1.3 0.24 2.3l-0.12 0.59-0.24 0.95c-0.12 0.59-0.36 1.3-0.47 2q-0.83 3.9-1.1 7.9c-0.47 5.3-0.36 11 0.59 16 0.71 4.3 1.9 8.4 3.7 12l-82 158z'/><path class='e' d='m699 148-23 125 23-34-25 62-20-5.2z'/><path class='d' d='m699 134c-1.5 21-44 160-45 162q-7.2-0.24-15-0.47c-12-0.36-25-0.59-37-0.71-5.9-0.12-12-0.24-17-0.24-0.83-6.4-2.3-12-3.8-19-0.24-0.83-0.47-1.8-0.71-2.7-1.5-5.8-3.2-11-5-17q-6.2-20-13-39c4.1 13 7.8 26 11 40 1.7 6.6 3.2 13 4.6 20 1.2 5.9 2.3 12 2.7 18h-20c-4.7 0.12-9.2 0.12-14 0.24-8.5 0.24-16 0.47-22 0.95-2.3-3.2-4.9-6.2-7.6-8.9-3-3.1-6-5.9-9.4-8.7q-7.1-6.2-15-12-2.7-2-5.5-4c6.4 5.5 13 11 18 17 3 3.1 5.8 6.2 8.5 9.4 1.9 2.3 3.6 4.6 5.2 7-1.4 0.24-2.7 0.36-3.8 0.47-11-13-25-23-39-32-14-9.5-29-18-45-25-7.6-4-15-7.5-23-11-7.8-3.4-16-6.6-23-10-7.6-3.6-15-7.5-22-12-5.9-3.9-12-8.5-16-14 1.9-2.4 4-4.9 6.3-6.9 1.5-1.4 3.1-2.8 4.7-4 1.5-1.1 3.1-2.1 4.6-2.6 1.5-0.71 2.7-0.71 3.7-0.47 0.24 0.12 0.24 0 0.71 0.36l1.2 0.71c0.71 0.59 1.4 1.1 2.3 1.8l5 4.3c1.7 1.4 3.7 3.1 6.5 4.1 1.4 0.47 3.2 0.83 4.9 0.59 0.95 0 1.8-0.24 2.5-0.59 0.83-0.36 1.7-0.71 2.1-1.1 2.7-1.8 4-3.9 5.5-5.9 2.6-4.1 4.3-7.9 6.3-12 3.6-6.8 7.2-14 12-18q0.71-0.83 1.5-1.4c3-2.1 6.3-3.3 10-3.2q1.4 0 2.7 0.36c0.95 0.12 1.9 0.24 2.8 0.59l2.8 0.83c1.3 0.47 2.6 0.83 3.9 0.95 5.2 0.71 10-0.47 14-2.1s8.4-3.9 12-6.3c15-10 27-23 39-35 5.8-6.4 12-12 19-17q5.1-3.4 11-5.9 5.9-2.6 12-4.3c4.9-1.3 9.8-2.1 15-2.6q5-0.36 10-0.24c4.1-0.12 8.4 0.47 13 0.83 4.1 0.59 8.3 1.4 13 1.9 8.9 0.71 18 0.36 27-0.71 4.4-0.59 8.8-1.3 13-2.3 2.3-0.47 4-0.59 6-0.83 2 0.12 4-0.12 6 0.36 8.1 1.3 16 5.1 23 9.8q1.7 1.1 3.2 2.3c5.8 4.3 11 9.2 16 14l3 3.4c0 0.12 5 7.6 3.6 28z'/><path class='b' d='m676 88c0.36 68-34 195-37 208q-0.24 1.1-0.24 1.1l-37-1.8c-2.4-103-28-188-39-218q5-0.36 10-0.24c4.1-0.12 8.4 0.47 13 0.83 4.1 0.59 8.3 1.4 13 1.9 8.9 0.71 18 0.36 27-0.71 4.4-0.59 8.8-1.3 13-2.3 2.3-0.47 4-0.59 6-0.83 2 0.12 4-0.12 6 0.36 8.1 1.3 16 5.1 23 9.8q1.7 1.1 3.2 2.3z'/><path class='b' d='m548 300-29-3c-3.7-7.1-14-18-27-30-38-34-100-78-100-78 2.7-1.8 4-3.9 5.5-5.9 2.6-4.1 4.3-7.9 6.3-12 3.6-6.8 7.2-14 12-18 70 34 119 122 129 143 1.4 2.7 2.3 4.3 2.3 4.3z'/><path class='b' d='m580 295h-20c-6.5-52-105-147-105-147 4.4-1.7 8.4-3.9 12-6.3 15-10 27-23 39-35 5.8-6.4 12-12 19-17q5.1-3.4 11-5.9c35 78 42 154 44 190 0.47 14 0.24 21 0.24 21z'/><path class='f' d='m767 417q-2.6-0.71-5.2-1.3c-22-5.5-45-12-67-19-11-10-18-21-23-29-0.24-0.36-0.36-0.59-0.47-0.95-4.1-7.8-6.3-14-7.2-17-0.12-0.24-0.12-0.47-0.12-0.47 9.1-0.47 16-1.1 19-1.7 3.4-0.71 7.1-0.71 11-0.36 7.6 0.83 14 3.4 16 4.3 3.7 5.2 32 45 56 67z'/><path class='d' d='m762 415c-22-5.5-45-12-67-19-11-10-18-21-23-29-0.24-0.36-0.36-0.59-0.47-0.95-4.3-8.7-6.6-16-7.2-17-0.12-0.24-0.12-0.47-0.12-0.47s7.7-1.1 19-1.7c3.3-0.24 6.9-0.36 11-0.36 7.6 0.83 14 3.4 16 4.3 3.7 5.2 32 45 56 67q-2.6-0.71-5.2-1.3z'/><path class='b' d='m725 405s-28-22-29-44l20 20s-21-29-22-35c0 0-15-6.4-33 0 0 0 13 35 34 50 0 0 19 9.2 29 9.4z'/><path class='f' d='m686 393q-6.4-2.1-13-4.3c-6.2-2.3-12-4.4-18-6.6-5.5-2-11-4-16-6q-14-5.3-28-11-12-4.6-24-9.4c-3.4-1.3-6.9-2.7-10-4.1 7.4-0.24 17-0.47 28-0.95 7.8-0.24 16-0.59 24-0.83h0.12c4.4-0.24 8.8-0.47 13-0.59 6.6-0.36 13-0.59 19-0.95 1.4 5.8 7.1 24 26 45z'/><path class='d' d='m655 382c-23-8.4-46-17-69-26-3.4-1.3-6.9-2.7-10-4.1 15-0.47 42-1.3 66-2.4q7.2 17 13 33z'/><path class='b' d='m639 376q-14-5.3-28-11c-2.4-6.6-4.5-11-5.9-14-0.95-2-1.5-3.1-1.5-3.1l26 2.3h0.12c3.9 7 7.2 16 10 26z'/><path class='e' d='m514 356c-3.1-1.7-6.3-3.3-9.2-5.1l-6.8-4.5c-1.2 1.5-2.5 4.3-1.7 8.2v0.59s0.12 0.71 1.2 1.4c1.4 0.95 5.8 2.6 18 0.12z'/><path class='f' d='m993 1024c-0.59 16-4.4 32-13 45-8.4 13-21 23-36 29-1.9 0.71-3.7 1.5-5.7 2.1l-5.9 1.9c-4 1.2-7.9 2.6-12 3.7-8.2 2-16 4.3-25 5.9-33 7.1-67 12-101 15-34 3.3-67 5.5-101 6.4-4.5-0.59-8.4-0.71-12-0.71q-6.3 0.12-12 0.47-6.2 0.47-12 1.1l-6 0.71-1.5 0.12-0.47 0.12-0.71 0.12-3 0.12c-16 0.71-31 1.8-47 2.3-31 0.83-63 1.2-94-0.83-31-1.8-62-4.9-93-11-7.5-1.8-15-3.3-23-5.2-7.4-2.1-15-4-22-6.5-3.7-1.2-7.2-2.4-11-3.8-3.6-1.4-7.1-2.7-10-4.4l-5.1-2.3-4.7-2.5c-1.7-0.83-3.1-1.8-4.6-2.6q-1.2-0.71-2.1-1.4l-4.6-3.2-3.1-0.36c-16-2-34-6.8-46-15-6.2-4.4-11-9.4-12-15l-1.2-5.7-0.83-6.3c-0.47-4.3-0.83-8.7-1.1-13-0.83-18-0.59-36 0-54 0.71-18 1.7-36 3.1-54l0.12-0.83v-0.59c-3.7-53-1.5-107 7.5-160 4.6-26 11-53 19-78 4.1-13 8.8-25 14-37 3.1-5.8 6.2-12 9.5-17l10-17c21-33 43-64 66-95 9.1-12 18-25 28-37 11-15 23-30 34-44q33-42 66-83c0.12-0.12 0.12-0.12 0.24-0.12l2.1 1.2 9.6 4.5c6.3 3.1 13 6.2 19 8.9q7.8 3.4 16 6.5 14 5.8 28 11 12 4.5 24 8.7c3.6 1.3 7 2.5 10 3.7q7.7 2.6 16 5.1c7 2.4 14 4.6 21 6.9 14 4.5 29 8.9 43 13 4.4 1.3 8.9 2.5 13 3.8 11 10 21 21 31 32 5.5 6.3 11 13 16 19 0.24 0.24 0.36 0.47 0.59 0.83 4.7 6.4 9.2 13 13 20-3.4-7.6-7.8-15-12-22-4.6-7-9.8-14-15-20q-2.1-2.7-4.4-5.3c-6.5-7.8-13-15-20-23 0.71 0.24 1.3 0.36 2 0.59 19 5.5 38 11 58 16l0.24 0.12h0.12q1.4 0.12 2.8 0.24c2.8 0.36 5.7 0.47 8.7 0.12 14 17 26 36 37 55 11 21 21 42 30 63 18 43 34 88 48 132 14 45 27 90 38 136 11 46 22 92 31 138v0.24l0.24 0.59c4.7 15 7.1 32 6.6 48z'/><path class='d' d='m876 645q-0.47-0.24-1.1-0.59c-33-18-57-48-67-85-7.2-25-21-51-36-75-6.2-9.6-13-19-19-27-6.3-8.2-13-16-18-22 19 5.5 38 11 58 16l0.24 0.12h0.12q1.4 0.12 2.8 0.24c37 83 80 190 81 193z'/><path class='c' d='m722 318c0 0.12-0.12 0.47-0.36 1.2-0.59 1.2-1.8 3-4.7 4.5-1.5 0.83-3.4 0.59-5.2-0.36-5.3-3.2-16-5.2-32-5.8-3.7-0.36-64-7-114-7-25 0-47 1.7-59 6.4l-0.47 0.24-3.7 4h-0.24c-1.3-0.71-3.2-2-4.7-3.9q-0.71-0.95-1.2-2.3l-0.12-0.24s-0.83-1.8 0.24-4c1.1-2.1 5-6.3 18-8.7 27-4.7 181-0.95 199 3.4 0.36 0.12 9.5 3.7 7.9 12z'/><path class='c' d='m813 438c0 0.36-0.59 1.8-1.3 2.5-1.5 1.8-4.5 2.7-7.7 3.2-3.2 0.36-6.8 0.12-10-0.36-27-7-54-15-80-23-27-7.9-53-16-80-25-27-8.9-53-18-79-29-6.4-2.5-13-5.3-19-8.2l-9.5-4.1-19-9.2-13-7.8c-0.71-0.36-1.8-0.83-1.9-1.1-0.47-0.47-1.1-0.95-1.4-1.5-1.5-2-1.8-4.6-0.71-7.2 0.47-0.47 1.2-0.95 1.8-1.4 0.83-0.47 1.7-0.83 2.5-1.2q1.2-0.59 2.6-0.71c0.95-0.12 1.8 0 2.3-0.12l1.5 0.71c0.59 0.36 1.1 0.59 1.3 0.59l2.1 1.1 5.3 2.4 32 14q21 9.4 43 18c29 12 57 23 87 34 29 11 59 20 89 28 3.8 0.95 7.6 2 11 2.8l11 2.4c7.7 1.7 16 2.5 23 3.4l3 0.24 0.59 0.12h0.24c0.24 0.12 0.47 0.12 0.71 0.36 1.1 0.36 1.7 0.95 2 1.7q0.71 1.2 0.47 3.4z'/><path class='g' d='m1e3 999c1.3 8.8 2.1 18 1.9 27-0.36 18-4.4 37-14 52-4.9 7.9-11 15-18 21-7.4 5.8-15 10-24 14-2.1 0.83-4.3 1.8-6.3 2.5l-6.3 2c-4.1 1.3-8.3 2.8-12 4-8.4 2.3-17 4.7-25 6.5-34 7.8-68 13-102 17-34 3.8-69 6.5-103 7.8l-0.71 0.12-0.95-0.12c-3-0.47-6.6-0.47-10-0.47-3.7 0.12-7.5 0.36-11 0.71q-5.7 0.47-11 1.1l-7.2 0.95-1.7 0.24-3.1 0.12c-16 1.1-32 2.4-48 3.1-32 1.3-64 2.1-96 0.47-32-1.3-64-4-96-10-7.9-1.7-16-3.2-24-5.1-7.9-2.1-16-4-24-6.6-4-1.3-7.9-2.5-12-4-3.9-1.4-7.8-2.8-12-4.6l-5.8-2.5-5.7-3c-1.9-0.83-3.9-2.1-5.8-3.2q-1.4-0.71-3-1.8-0.24-0.12-0.36-0.36c-9.1-1.4-17-3.4-26-6.3-9.5-3.2-19-7.4-28-14-4.4-3.2-8.5-7.1-12-12-1.8-2.3-3.2-5.1-4.7-7.7-1.2-2.7-2.3-5.7-3.1-8.5l-1.4-7.8-0.83-7.4q-0.59-7.2-0.83-14c-0.47-19 0.24-37 1.3-56 1.2-18 2.6-37 4.5-55-2.5-55 0.95-109 11-163 5.2-27 12-54 21-80 4.6-13 9.5-26 16-38 3.3-6 6.6-12 10-18l11-17c30-45 64-88 97-131 32-41 66-81 99-121q-5.1 0.83-9.1 0.95-6.8 0-10-2.6c-2.1-1.7-2.5-3.7-2.6-4.5-1.1-5.3 0.71-9.1 2.4-11l-3-1.9c-0.83-0.59-1.4-0.83-2.4-1.8q-1.2-1.1-2.1-2.5c-1.2-1.8-1.9-4-1.9-6.3 0-2.3 0.59-4.3 1.5-6.2h0.12l0.12-0.24 0.24-0.24c0.95-1.1 1.8-1.7 2.8-2.4q1.5-0.95 3.3-1.7c0.59-0.24 1.3-0.36 2-0.47-0.95-1.2-1.8-2.5-2.4-3.9-0.71-1.4-1.4-4.6 0.24-7.9 2.3-4.6 8.2-8.1 18-10-4.7-5-10-9.8-16-14-6.6-5.1-14-10-21-14-14-9.1-29-17-44-24-7.6-3.8-15-7.1-23-10-7.8-3.3-16-6.3-24-9.8-7.9-3.4-16-7.4-23-12-7.4-4.7-15-10-20-18l-1.7-2.3 1.9-2.3c2.8-3.8 5.8-7 9.1-10 3.4-3.1 6.9-6.2 12-8.2 2.4-0.95 5.7-1.5 9-0.47 1.8 0.59 2.7 1.4 3.8 2 0.95 0.83 1.9 1.5 2.8 2.3l4.9 4.3c1.5 1.4 3.1 2.5 4.3 3 1.2 0.36 1.7 0.36 2.8-0.36 1.1-0.59 2.3-2.1 3.3-3.6 2-3.2 3.9-7.4 5.9-11 2-3.9 4.1-7.8 6.6-12 2.6-3.8 5.5-7.6 9.5-11 4-3.1 9.4-4.7 14-4.5q1.9 0 3.7 0.47c1.2 0.12 2.4 0.36 3.6 0.71l3.3 1.1c0.83 0.24 1.7 0.59 2.5 0.59 7.1 1.1 15-2.8 22-7.2 14-9.1 26-22 38-34 5.8-6.3 13-13 20-18 7.5-4.9 16-8.4 25-11 17-4.6 36-3 53 0.24 8.4 0.71 17 0.47 25-0.47 4.3-0.59 8.4-1.2 13-2.1 2-0.36 4.5-0.59 6.8-0.83 2.4 0.12 4.7-0.12 7 0.47 9.1 1.4 17 5.7 25 11 5.2 3.7 10 7.7 15 12-0.59-8.5 2.8-17 8.3-23 7-8.4 16-14 26-18s19-8.1 30-9.8c5.2-0.83 11-1.2 16-0.59 1.4 0.12 2.8 0.36 4.1 0.71 1.4 0.24 2.8 0.71 4.3 1.4 2.6 1.2 5.7 3 7.1 6.5 0.71 1.7 1.1 3.7 0.71 5.3l-0.24 1.3-0.12 0.95c-0.12 0.59-0.36 1.2-0.36 1.8-0.47 2.4-0.83 4.9-0.95 7.2-0.36 5-0.12 9.8 0.71 15 1.8 9.6 6.3 18 13 26 3.2 3.7 7 6.5 11 10 4 3.3 7.9 6.8 12 10 7.6 7.4 15 15 21 24v0.12l1.1 1.7-0.95 1.8c-2 4.3-4.3 8.1-6.8 12q-3.7 5.7-8.1 11-4.3 5.2-9.2 9.8c-3.2 3.1-6.6 5.8-10 8.4-18 16-37 32-54 50-8.7 8.5-17 17-25 26-4 4.6-8.1 9.1-12 14-3.1 4-5.7 8.3-7.7 13 2.6 0.36 4.6 0.71 5.9 0.95 4.7 1.8 13 7.6 11 17 0 0-0.36 5.3-7.4 9q-0.12 0-0.12 0c3.1 2.3 5.9 6 5.2 12-0.12 0.47-1.5 7.4-8.3 10 7.6 11 38 52 61 69l7.8 1.5c7.5 1.7 15 2.3 23 3.1l2.8 0.36 0.83 0.12c0.59 0.12 0.83 0.12 1.2 0.24q1.1 0.24 2 0.59c2.6 0.95 5.1 3.1 6.5 5.8 1.4 2.6 1.5 5.6 1.4 7.8-0.36 3.4-1.8 5.7-3.6 7.8-2.7 3-6 4.4-9.2 5.2 14 17 26 35 36 54 12 21 22 42 32 63 19 43 35 88 50 132 15 45 28 90 40 136 12 46 23 91 33 137 2.8 8.7 4.6 17 6 26zm-508-660 8.9 5.2 9.4 4.6 9.2 4.6 9.5 4.1c6.4 2.8 13 5.7 19 8.1 26 11 52 20 78 29 26 9 53 17 80 25 27 7.9 53 16 80 23 3.4 0.47 7 0.71 10 0.36 3.2-0.36 6.2-1.4 7.7-3.2 0.71-0.71 1.3-2.1 1.3-2.5q0.24-2.3-0.47-3.4c-0.36-0.71-0.95-1.3-2-1.8q-0.36-0.12-0.71-0.24h-0.24l-0.59-0.12-3-0.36c-7.8-0.83-16-1.5-23-3.3l-11-2.4c-3.8-0.83-7.6-1.9-11-2.8-30-7.7-60-18-89-28-29-11-58-22-87-34-14-5.9-29-12-43-18l-21-9.4-18-8.2q-0.36-0.24-1.4-0.71l-1.4-0.71c-0.47 0.12-1.4 0-2.3 0.12q-1.3 0.24-2.6 0.71t-2.5 1.2c-0.59 0.47-1.3 0.95-1.8 1.4-1.1 2.6-0.83 5.2 0.71 7.2 0.36 0.59 0.83 1.1 1.4 1.5 0.24 0.24 1.2 0.71 1.9 1.2zm162 8.2c-26 1.4-65 2.7-84 3.3q5.1 2.1 10 4.3c29 11 58 22 87 33 4.3 1.4 8.5 2.8 13 4.3-18-20-24-39-26-45zm52-19c-28-6.8-141 3.6-174 6.9l5.3 2.3q11 4.6 22 9.2c14-0.47 105-3.2 117-5.6 12-2.6 26 2.7 29 4 6-1.4 7.2-7.4 7.4-7.4 0.83-7.8-6.9-9.4-7.2-9.5zm-16-6.3c-4.1-0.59-9.4-1.2-16-1.4-1.5-0.12-135-15-171-1.1l-2 2.3 23 9.7c13-1.3 118-12 166-9.5zm-0.12-222 1.5 4.1 1.4-0.95c0.24 0.36 5.8 8.7 4.3 31-1.5 21-40 148-45 162 6.9 0.24 13 0.59 19 0.83l44-80-39 80c8.8 0.47 16 1.1 22 1.5 1.1-2.5 2-5 3.4-7.1l2.5-4c0.83-1.3 1.8-2.6 2.6-3.8 3.6-5.2 7.6-10 12-15 7.9-9.5 17-18 25-27 17-18 35-34 54-51l0.24-0.12c3.3-2.6 6.6-5.1 9.6-8.1q4.6-4.4 8.5-9.4 3.9-4.9 7.4-10c1.9-3 3.6-6 5.1-9.1-4.9-7.5-11-15-18-21-3.6-3.6-7.4-6.9-11-10-3.8-3.2-8.2-6.6-12-11-7.4-8.1-12-18-14-29-0.83-5.3-1.1-11-0.59-16 0.24-2.6 0.59-5.3 1.2-7.9 0.12-0.71 0.24-1.3 0.36-2l0.24-0.95 0.12-0.71c0.12-0.71 0-1.4-0.24-2.1-0.47-1.4-2.1-2.6-4-3.4-0.95-0.47-2-0.83-3.1-1.1-1.2-0.36-2.3-0.59-3.4-0.71-4.7-0.59-9.7-0.36-15 0.47-9.8 1.4-20 4.7-29 8.9-9.1 4.1-18 9.2-24 17-3.2 3.7-5.6 7.9-6.8 13-1.2 4.5-1.1 9.6 0.36 14zm-180 197q1.7-0.24 3.8-0.47-2.4-3.6-5.2-7c-2.6-3.2-5.5-6.3-8.4-9.4-5.9-6-12-12-19-17 6.9 4.9 14 10 20 16 3.2 2.7 6.3 5.6 9.4 8.7 2.6 2.7 5.2 5.7 7.6 8.9 13-0.95 33-1.3 55-1.2-0.47-5.9-1.5-12-2.7-18q-2-10-4.6-20c-3.3-13-7.1-27-11-40 4.7 13 9.1 26 13 39q3.1 10 5.7 20c1.5 6 3.1 12 3.9 18 23 0.12 48 0.71 70 1.5 0.71-2.5 43-141 45-162 1.4-20-3.4-28-3.6-28h0.12l-3.1-3.4c-5.7-6.2-12-12-19-17s-15-8.5-23-9.8c-2-0.47-4-0.24-6-0.36-2 0.36-3.8 0.36-6 0.95-4.3 0.95-8.7 1.5-13 2.1-8.8 1.1-18 1.5-27 0.71-4.6-0.47-8.7-1.3-13-1.9-4.3-0.36-8.4-0.83-13-0.83-8.4-0.12-17 0.71-25 2.8-8.1 2.1-16 5.6-23 10-7 4.6-13 10-19 17-12 13-24 25-39 35-3.8 2.4-7.7 4.6-12 6.3-4.4 1.7-9.2 3-14 2.1-1.3-0.12-2.6-0.47-3.8-0.95l-3-0.83c-0.95-0.36-1.9-0.47-2.7-0.59q-1.4-0.36-2.8-0.36c-3.7-0.12-7 0.95-10 3.2-5.9 4.5-9.8 12-14 20-2 3.9-3.7 7.7-6.4 12-1.4 2-2.7 4.1-5.3 5.9-0.59 0.47-1.4 0.83-2.1 1.1-0.83 0.36-1.7 0.59-2.5 0.59-1.8 0.36-3.6-0.12-5-0.59-2.8-1.1-4.9-2.7-6.5-4.1l-5-4.3c-0.71-0.71-1.5-1.2-2.3-1.8l-1.2-0.71c-0.36-0.36-0.47-0.24-0.71-0.36-0.83-0.24-2.1-0.24-3.7 0.47-3.2 1.2-6.4 3.8-9.4 6.6-2.1 2.1-4.3 4.5-6.3 6.9 4 5.2 9.7 9.8 16 14 6.8 4.6 14 8.5 22 12 7.5 3.4 16 6.6 23 10 7.8 3.6 16 7 23 11 15 7.6 30 16 45 25 14 9.5 27 19 39 32zm-19 17 0.12 0.12c1.3 3.3 4.3 5.2 5.9 6.2l0.24 0.12 3.7-4.1 0.47-0.24c12-4.7 34-6.4 59-6.4 50 0 110 6.6 114 7 15 0.59 26 2.6 31 5.8 1.8 1.1 3.7 1.2 5.2 0.36 4.7-2.4 5.1-5.6 5.1-5.7 1.5-8.7-7.5-12-7.9-12-18-4.4-172-8.2-199-3.4-13 2.5-17 6.5-18 8.8-1.1 2.1-0.24 3.9-0.24 4zm214 36c-2.7-1.2-16-6.2-27-3.9-2.8 0.59-9.7 1.2-19 1.8 1.9 6.8 8.9 27 30 48 22 7.2 44 14 67 19q2.6 0.59 5.3 1.3c-24-22-53-61-57-67zm-195 6.5-1.4-0.83c-3.1-1.7-6.2-3.3-9.2-5.1l-6.8-4.4c-1.2 1.4-2.5 4.1-1.7 8.1l0.12 0.36v0.24s0.12 0.71 1.1 1.4c1.4 0.95 5.8 2.6 18 0.24zm473 621-0.24-0.59v-0.24c-9.1-46-20-92-31-138-11-46-24-91-38-136-14-45-30-89-48-132-9.2-22-19-43-30-63-11-20-23-38-37-55-3.9 0.24-7.7 0-11-0.47h-0.24l-0.24-0.12c-20-5.1-40-11-60-16 8.5 9.1 17 18 25 28 5.3 6.5 10 13 15 20 4.6 7 9 14 12 22-3.8-7.5-8.4-14-13-21-4.9-6.6-10-13-16-19-9.8-11-20-22-31-32-4.4-1.3-8.8-2.5-13-3.8-27-7.8-54-16-80-25-27-9-53-19-79-30-6.5-2.7-13-5.8-19-8.9l-9.5-4.5-2.1-1.2q-0.24 0-0.36 0.12c-34 42-68 84-100 127-33 43-65 87-94 132l-10 17c-3.2 5.8-6.3 12-9.4 18-5.5 12-10 25-14 37-8.3 25-14 52-19 78-8.9 53-11 107-7.5 160v1.4c-1.5 18-2.5 36-3.2 55-0.59 18-0.83 36 0 54 0.24 4.4 0.59 8.8 1.1 13l0.83 6.3 1.2 5.7c1.5 5.9 5.9 11 12 15 12 8.4 30 13 46 15l3.1 0.36 3.2 2.1 1.5 1.1q0.83 0.71 2 1.4c1.5 0.83 3 1.8 4.6 2.6l9.8 4.9c3.3 1.5 6.9 2.8 10 4.3 3.4 1.4 7.1 2.6 11 3.8 7.1 2.5 15 4.5 22 6.5 7.4 1.9 15 3.4 23 5.2 30 6.2 61 9.2 93 11 31 2 63 1.7 94 0.83 16-0.47 31-1.5 47-2.3l2.8-0.24h1.3l1.5-0.24 6-0.71q6-0.59 12-0.95c4.1-0.36 8.2-0.47 12-0.59 3.9 0 7.8 0.12 12 0.71 34-0.95 68-3.1 101-6.3 34-3.3 68-7.8 101-15 8.3-1.7 16-3.9 25-5.9 4-1.1 8.1-2.5 12-3.7l6-1.9c1.9-0.59 3.7-1.4 5.6-2.1 15-5.9 28-16 36-29 8.4-13 12-29 13-45 0.59-16-1.9-33-6.6-48z' fill-rule='evenodd'/><path class='d' d='m993 1024c-0.59 16-4.4 32-13 45-8.4 13-21 23-36 29-1.9 0.71-3.7 1.5-5.7 2.1l-5.9 1.9c-4 1.2-7.9 2.6-12 3.7-8.2 2-16 4.3-25 5.9-33 7.1-67 12-101 15-34 3.3-67 5.5-101 6.4-4.5-0.59-8.4-0.71-12-0.71q-6.3 0.12-12 0.47-6.2 0.47-12 1.1l-6 0.71-1.5 0.12-0.47 0.12-0.71 0.12-3 0.12c-16 0.71-31 1.8-47 2.3-31 0.83-63 1.2-94-0.83-31-1.8-62-4.9-93-11-7.5-1.8-15-3.3-23-5.2-7.4-2.1-15-4-22-6.5-3.7-1.2-7.2-2.4-11-3.8-3.6-1.4-7.1-2.7-10-4.4l-5.1-2.3-4.7-2.5c-1.7-0.83-3.1-1.8-4.6-2.6q-1.2-0.71-2.1-1.4l-4.6-3.2-3.1-0.36c-16-2-34-6.8-46-15-6.2-4.4-11-9.4-12-15l-1.2-5.7-0.83-6.3c-0.47-4.3-0.83-8.7-1.1-13-0.83-18-0.59-36 0-54 0.59-15 1.3-30 2.4-44 0.24-3.4 0.47-6.9 0.71-10l0.12-0.83v-0.59c-3.7-53-1.5-107 7.5-160 4.6-26 11-53 19-78 4.1-13 8.8-25 14-37 3.1-5.8 6.2-12 9.5-17l10-17c21-33 43-64 66-95 0 0-152 279-43 517 0 0 82 103 364 44 0 0 65-15 87-67l-7.9 86s117-9.5 138-62c21-53 35-256-90-533 11 21 21 42 30 63 18 43 34 88 48 132 14 45 27 90 38 136 11 46 22 92 31 138v0.24l0.24 0.59c4.7 15 7.1 32 6.6 48z'/><path class='b' d='m324 1095c-16-2-34-6.8-46-15-6.2-4.4-11-9.4-12-15l-1.2-5.7-0.83-6.3c-0.47-4.3-0.83-8.7-1.1-13-0.83-18-0.59-36 0-54 0.59-15 1.3-30 2.4-44 16 102 59 154 59 154z'/><path class='d' d='m564 380c-2.4 15-6 36-12 63-21 92-156 173-149 127 7.4-46 84-163 84-163l-36 35q33-42 66-83h0.24l2.3 1.1 9.5 4.6c6.3 3 13 6.2 19 8.8q7.7 3.4 16 6.6z'/><path class='b' d='m533 365-53 125s72-72 72-116z'/><path class='d' d='m684 669c-15 26-88-62-76-147 7.2-52-3.4-100-13-130 11 4.3 23 8.4 35 12 12 4.1 25 8.1 37 12 49 147 30 229 17 252z'/><path class='b' d='m655 508c-29-24-30-72-30-72-1.1-13-2.8-25-5-35 3.6 1.3 7 2.5 10 3.7q7.7 2.6 16 5.1c7.8 47 9 98 9 98z'/><path class='b' d='m835 155c-1.5 3.1-3.2 6.2-5.1 9q-3.4 5.5-7.4 10c-2.6 3.3-5.5 6.4-8.5 9.4-3 2.8-6.3 5.5-9.6 7.9l-0.24 0.24h-0.12c-18 16-36 33-54 51-8.7 8.9-17 18-25 27l92-136c6.6 6.6 13 14 18 21z'/><path class='b' d='m516 297c-11-13-25-23-39-32-14-9.5-29-18-45-25-7.6-4-15-7.5-23-11-7.8-3.4-16-6.6-23-10-7.6-3.6-15-7.5-22-12-5.9-3.9-12-8.5-16-14 1.9-2.4 4-4.9 6.3-6.9 1.5-1.4 3.1-2.8 4.7-4 0 0 35 36 74 52 0 0 65 36 83 64z'/><path class='e' d='m696 323c-7.4-0.36-16-0.47-26-0.24-101-3.3-148 6.6-148 6.6l-15-6.6 2.1-2.3c35-14 169 0.95 171 1.1 6.8 0.24 12 0.83 16 1.4z'/><path class='e' d='m813 438c0 0.36-0.59 1.8-1.3 2.5-1.5 1.8-4.5 2.7-7.7 3.2-3.2 0.36-6.8 0.12-10-0.36-27-7-54-15-80-23-27-7.9-53-16-80-25-27-8.9-53-18-79-29-6.4-2.5-13-5.3-19-8.2l-9.5-4.1-19-9.2-13-7.8c-0.71-0.36-1.8-0.83-1.9-1.1-0.47-0.47-1.1-0.95-1.4-1.5-1.5-2-1.8-4.6-0.71-7.2 0.47-0.47 1.2-0.95 1.8-1.4 0.83-0.47 1.7-0.83 2.5-1.2 0 0 16 30 198 83 0 0 92 33 120 30z'/><path class='e' d='m719 339c-0.47 1.7-2.4 5.5-7 6.6-3.3-1.3-17-6.6-29-4-12 2.4-102 5.1-117 5.6-4.6-2-9.4-3.9-14-5.8 2.5-0.12 101-1.2 129-7.1 15-3.1 29 0.36 38 4.7z'/><path class='e' d='m722 319c-0.59 1.2-1.8 3-4.7 4.5-1.5 0.83-3.4 0.59-5.2-0.36-5.3-3.2-16-5.2-32-5.8-3.7-0.36-64-7-114-7-25 0-47 1.7-59 6.4l-0.47 0.24-3.7 4h-0.24c-1.3-0.71-3.2-2-4.7-3.9 0 0-3.3-10 40-12 44-1.4 147 2.1 163 6.8 6.5 2 14 4.4 21 7.1z'/><path class='h' d='m424 601s101-25 139-165c0 0-28 200-139 165z'/><path class='h' d='m876 655s-58-10-71-73c0 0-3.2 80 71 73z'/><path class='i' d='m524 340s99 51 146 57c0 0-123-48-146-57z'/><path class='i' d='m606 333s95-5.3 107-1.1c0 0-53-9.6-107 1.1z'/><path class='i' d='m607 303s88 0.12 104 10c0 0-22-16-104-10z'/> <circle cx='368' cy='1040' r='68' style='fill:${:fill[0]};stroke-linecap:round;stroke-linejoin:round;stroke-width:4.1;stroke:#000;display:${:display[0]}'/> <circle cx='504' cy='1067' r='68' style='fill:${:fill[1]};stroke-linecap:round;stroke-linejoin:round;stroke-width:4.1;stroke:#000;display:${:display[1]}'/> <circle cx='642' cy='1069' r='68' style='fill:${:fill[2]};stroke-linecap:round;stroke-linejoin:round;stroke-width:4.1;stroke:#000;display:${:display[2]}'/> <circle cx='781' cy='1058' r='68' style='fill:${:fill[3]};stroke-linecap:round;stroke-linejoin:round;stroke-width:4.1;stroke:#000;display:${:display[3]}'/> <circle cx='917' cy='1038' r='68' style='fill:${:fill[4]};stroke-linecap:round;stroke-linejoin:round;stroke-width:4.1;stroke:#000;display:${:display[4]}'/> <circle cx='333' cy='904' r='68' style='fill:${:fill[5]};stroke-linecap:round;stroke-linejoin:round;stroke-width:4.1;stroke:#000;display:${:display[5]}'/> <circle cx='465' cy='936' r='68' style='fill:${:fill[6]};stroke-linecap:round;stroke-linejoin:round;stroke-width:4.1;stroke:#000;display:${:display[6]}'/> <circle cx='601' cy='940' r='68' style='fill:${:fill[7]};stroke-linecap:round;stroke-linejoin:round;stroke-width:4.1;stroke:#000;display:${:display[7]}'/> <circle cx='736' cy='931' r='68' style='fill:${:fill[8]};stroke-linecap:round;stroke-linejoin:round;stroke-width:4.1;stroke:#000;display:${:display[8]}'/> <circle cx='873' cy='905' r='68' style='fill:${:fill[9]};stroke-linecap:round;stroke-linejoin:round;stroke-width:4.1;stroke:#000;display:${:display[9]}'/> <circle cx='429' cy='803' r='68' style='fill:${:fill[10]};stroke-linecap:round;stroke-linejoin:round;stroke-width:4.1;stroke:#000;display:${:display[10]}'/> <circle cx='565' cy='807' r='68' style='fill:${:fill[11]};stroke-linecap:round;stroke-linejoin:round;stroke-width:4.1;stroke:#000;display:${:display[11]}'/> <circle cx='703' cy='798' r='68' style='fill:${:fill[12]};stroke-linecap:round;stroke-linejoin:round;stroke-width:4.1;stroke:#000;display:${:display[12]}'/> <circle cx='838' cy='773' r='68' style='fill:${:fill[13]};stroke-linecap:round;stroke-linejoin:round;stroke-width:4.1;stroke:#000;display:${:display[13]}'/> <circle cx='369' cy='682' r='68' style='fill:${:fill[14]};stroke-linecap:round;stroke-linejoin:round;stroke-width:4.1;stroke:#000;display:${:display[14]}'/> <circle cx='507' cy='683' r='68' style='fill:${:fill[15]};stroke-linecap:round;stroke-linejoin:round;stroke-width:4.1;stroke:#000;display:${:display[15]}'/> <circle cx='642' cy='676' r='68' style='fill:${:fill[16]};stroke-linecap:round;stroke-linejoin:round;stroke-width:4.1;stroke:#000;display:${:display[16]}'/> <circle cx='773' cy='653' r='68' style='fill:${:fill[17]};stroke-linecap:round;stroke-linejoin:round;stroke-width:4.1;stroke:#000;display:${:display[17]}'/></svg>"
            }
        }
    ]
}